JcUtility/__init__.py
JcUtility-0.0.2.dist-info/METADATA
JcUtility-0.0.2.dist-info/WHEEL
JcUtility-0.0.2.dist-info/top_level.txt
JcUtility-0.0.2.dist-info/RECORD
